examples/clinical_trials/main.py
examples/quickstart/main.py
siare/__init__.py
siare/builders.py
siare/cli.py
siare/py.typed
siare/adapters/__init__.py
siare/adapters/base.py
siare/adapters/vector_search.py
siare/adapters/web_search.py
siare/adapters/wikipedia_search.py
siare/benchmarks/__init__.py
siare/benchmarks/adapters.py
siare/benchmarks/base.py
siare/benchmarks/evolution_runner.py
siare/benchmarks/hotpotqa.py
siare/benchmarks/natural_questions.py
siare/benchmarks/publication_suite.py
siare/benchmarks/quality_gate_suite.py
siare/benchmarks/rag_runner.py
siare/benchmarks/reporter.py
siare/benchmarks/reproducibility.py
siare/benchmarks/runner.py
siare/benchmarks/self_improvement_benchmark.py
siare/benchmarks/comparison/__init__.py
siare/benchmarks/comparison/baselines.py
siare/benchmarks/corpus/__init__.py
siare/benchmarks/corpus/index_manager.py
siare/benchmarks/corpus/loader.py
siare/benchmarks/corpus/wikipedia_loader.py
siare/benchmarks/datasets/__init__.py
siare/benchmarks/datasets/beir.py
siare/benchmarks/datasets/frames.py
siare/benchmarks/metrics/__init__.py
siare/benchmarks/metrics/evolution_metrics.py
siare/benchmarks/metrics/integration.py
siare/benchmarks/metrics/retrieval.py
siare/benchmarks/metrics/retrieval_evolution.py
siare/benchmarks/reports/__init__.py
siare/benchmarks/reports/evolution_value_report.py
siare/benchmarks/reports/self_improvement_report.py
siare/benchmarks/scripts/__init__.py
siare/benchmarks/scripts/demonstrate_evolution_value.py
siare/benchmarks/scripts/download_beir_corpus.py
siare/benchmarks/scripts/run_baseline.py
siare/benchmarks/scripts/run_evolution_benchmark.py
siare/benchmarks/scripts/run_publication_benchmark.py
siare/benchmarks/scripts/run_rag_benchmark.py
siare/benchmarks/scripts/run_self_improvement_benchmark.py
siare/benchmarks/scripts/verify_benchmark.py
siare/benchmarks/sops/__init__.py
siare/benchmarks/sops/evolvable_rag.py
siare/benchmarks/sops/multihop_rag.py
siare/benchmarks/sops/rag_retriever.py
siare-1.0.0.dist-info/licenses/LICENSE
siare-1.0.0.dist-info/METADATA
siare-1.0.0.dist-info/WHEEL
siare-1.0.0.dist-info/entry_points.txt
siare-1.0.0.dist-info/top_level.txt
siare-1.0.0.dist-info/RECORD
