Metadata-Version: 2.4
Name: siare
Version: 1.0.0
Summary: Self-Improving Agentic RAG Engine - Evolve multi-agent RAG pipelines using Quality-Diversity optimization
Author-email: Daniel Bentes <daniel@synapti.ai>
Maintainer-email: Daniel Bentes <daniel@synapti.ai>
License-Expression: MIT
Project-URL: Homepage, https://siare.dev
Project-URL: Documentation, https://github.com/synaptiai/siare#readme
Project-URL: Repository, https://github.com/synaptiai/siare
Project-URL: Issues, https://github.com/synaptiai/siare/issues
Project-URL: Changelog, https://github.com/synaptiai/siare/blob/main/CHANGELOG.md
Keywords: rag,retrieval-augmented-generation,evolutionary-algorithms,quality-diversity,map-elites,llm,agents,multi-agent,prompt-optimization
Classifier: Development Status :: 4 - Beta
Classifier: Intended Audience :: Developers
Classifier: Intended Audience :: Science/Research
Classifier: Operating System :: OS Independent
Classifier: Programming Language :: Python :: 3
Classifier: Programming Language :: Python :: 3.12
Classifier: Programming Language :: Python :: 3.13
Classifier: Topic :: Scientific/Engineering :: Artificial Intelligence
Classifier: Topic :: Software Development :: Libraries :: Python Modules
Classifier: Typing :: Typed
Requires-Python: >=3.12
License-File: LICENSE
Requires-Dist: pydantic>=2.0.0
Requires-Dist: numpy>=1.24.0
Requires-Dist: pyyaml>=6.0
Requires-Dist: python-dateutil>=2.8.0
Requires-Dist: typing-extensions>=4.0.0
Requires-Dist: click>=8.0.0
Requires-Dist: rich>=13.0.0
Requires-Dist: questionary>=2.0.0
Provides-Extra: llm
Requires-Dist: openai>=1.0.0; extra == "llm"
Requires-Dist: anthropic>=0.18.0; extra == "llm"
Provides-Extra: embeddings
Requires-Dist: sentence-transformers>=2.2.0; extra == "embeddings"
Provides-Extra: full
Requires-Dist: siare[embeddings,llm]; extra == "full"
Requires-Dist: scikit-learn>=1.3.0; extra == "full"
Provides-Extra: benchmarks
Requires-Dist: datasets>=2.14.0; extra == "benchmarks"
Requires-Dist: beir>=2.0.0; extra == "benchmarks"
Requires-Dist: plotly>=5.18.0; extra == "benchmarks"
Requires-Dist: matplotlib>=3.7.0; extra == "benchmarks"
Provides-Extra: dev
Requires-Dist: pytest>=7.0.0; extra == "dev"
Requires-Dist: pytest-cov>=4.0.0; extra == "dev"
Requires-Dist: pytest-asyncio>=0.21.0; extra == "dev"
Requires-Dist: ruff>=0.1.0; extra == "dev"
Requires-Dist: pyright>=1.1.0; extra == "dev"
Dynamic: license-file
